Metadata-Version: 2.1
Name: egen111222-my-docs-libs
Version: 1.0
Summary: Python Distribution Utilities
Author: Kirill
Author-email: egen13@ukr.net
